key_spyder/__init__.py
key_spyder/crawler.py
key_spyder/defaults.py
key_spyder/logs.py
key_spyder/sitemap.py
key_spyder-1.4.2.dist-info/METADATA
key_spyder-1.4.2.dist-info/WHEEL
key_spyder-1.4.2.dist-info/entry_points.txt
key_spyder-1.4.2.dist-info/top_level.txt
key_spyder-1.4.2.dist-info/RECORD
