Metadata-Version: 2.1
Name: key-spyder
Version: 1.4.2
Summary: A Web-Crawler that detects keywords in webpages.
Home-page: https://github.com/ChemicalLuck/key-spyder
Author: ChemicalLuck
License: MIT
Keywords: crawler,bs4,beautifulsoup4,sitemap
Platform: UNKNOWN
Classifier: Environment :: Console
Classifier: Intended Audience :: Developers
Classifier: License :: OSI Approved :: MIT License
Classifier: Programming Language :: Python :: 3 :: Only
Classifier: Topic :: Internet :: WWW/HTTP :: Indexing/Search
Classifier: Topic :: Internet :: WWW/HTTP :: Site Management
Classifier: Topic :: Internet
Classifier: Topic :: Software Development :: Libraries :: Python Modules
Requires-Python: >=3.6
Requires-Dist: requests
Requires-Dist: requests-cache
Requires-Dist: beautifulsoup4
Requires-Dist: pandas
Requires-Dist: lxml
